mcp_server_mac_brightness/__init__.py
mcp_server_mac_brightness/__main__.py
mcp_server_mac_brightness/controller.py
mcp_server_mac_brightness/server.py
mcp_server_mac_brightness-0.1.4.dist-info/METADATA
mcp_server_mac_brightness-0.1.4.dist-info/WHEEL
mcp_server_mac_brightness-0.1.4.dist-info/entry_points.txt
mcp_server_mac_brightness-0.1.4.dist-info/licenses/LICENSE
mcp_server_mac_brightness-0.1.4.dist-info/RECORD
