Metadata-Version: 2.4
Name: mcp_server_mac_brightness
Version: 0.1.4
Summary: A Model Context Protocol server for controlling Mac screen brightness
Author: T0UGH
License: MIT
License-File: LICENSE
Requires-Python: >=3.10
Requires-Dist: mcp[cli]>=1.3.0
Requires-Dist: pyobjc>=10.1
